setup.py
qlda/MLOPE.py
qlda/RunMLOPE.py
qlda/__init__.py
qlda/infering.py
qlda/per_vb.py
qlda/utilities.py
qlda.egg-info/PKG-INFO
qlda.egg-info/SOURCES.txt
qlda.egg-info/dependency_links.txt
qlda.egg-info/not-zip-safe
qlda.egg-info/requires.txt
qlda.egg-info/top_level.txt