Metadata-Version: 1.0
Name: qlda
Version: 0.1.6
Summary: Lda-MLOPE
Home-page: https://github.com/Quangbd/qlda
Author: Quang Bui Duc
Author-email: quangbd.hust@gmail.com
License: NONE
Platform: UNKNOWN
